pyrin/__init__.py
pyrin/admin/__init__.py
pyrin/admin/api.py
pyrin/admin/component.py
pyrin/admin/decorators.py
pyrin/admin/enumerations.py
pyrin/admin/exceptions.py
pyrin/admin/hooks.py
pyrin/admin/interface.py
pyrin/admin/manager.py
pyrin/admin/services.py
pyrin/admin/page/__init__.py
pyrin/admin/page/base.py
pyrin/admin/page/decorators.py
pyrin/admin/page/enumerations.py
pyrin/admin/page/exceptions.py
pyrin/admin/page/mixin.py
pyrin/admin/page/schema.py
pyrin/admin/security/__init__.py
pyrin/admin/security/authenticators.py
pyrin/admin/security/authorizers.py
pyrin/admin/security/exceptions.py
pyrin/api/__init__.py
pyrin/api/component.py
pyrin/api/decorators.py
pyrin/api/exceptions.py
pyrin/api/hooks.py
pyrin/api/manager.py
pyrin/api/services.py
pyrin/api/router/__init__.py
pyrin/api/router/component.py
pyrin/api/router/decorators.py
pyrin/api/router/exceptions.py
pyrin/api/router/manager.py
pyrin/api/router/services.py
pyrin/api/router/structs.py
pyrin/api/router/handlers/__init__.py
pyrin/api/router/handlers/base.py
pyrin/api/router/handlers/exceptions.py
pyrin/api/router/handlers/protected.py
pyrin/api/router/handlers/public.py
pyrin/api/schema/__init__.py
pyrin/api/schema/component.py
pyrin/api/schema/exceptions.py
pyrin/api/schema/manager.py
pyrin/api/schema/services.py
pyrin/api/schema/structs.py
pyrin/api/swagger/__init__.py
pyrin/api/swagger/base.py
pyrin/api/swagger/component.py
pyrin/api/swagger/decorators.py
pyrin/api/swagger/enumerations.py
pyrin/api/swagger/exceptions.py
pyrin/api/swagger/interface.py
pyrin/api/swagger/manager.py
pyrin/api/swagger/services.py
pyrin/api/swagger/tags/__init__.py
pyrin/api/swagger/tags/base.py
pyrin/api/swagger/tags/exceptions.py
pyrin/api/swagger/tags/protected.py
pyrin/api/swagger/tags/public.py
pyrin/application/__init__.py
pyrin/application/base.py
pyrin/application/container.py
pyrin/application/decorators.py
pyrin/application/enumerations.py
pyrin/application/exceptions.py
pyrin/application/hooks.py
pyrin-0.6.3.dist-info/LICENSE
pyrin-0.6.3.dist-info/METADATA
pyrin-0.6.3.dist-info/WHEEL
pyrin-0.6.3.dist-info/entry_points.txt
pyrin-0.6.3.dist-info/top_level.txt
pyrin-0.6.3.dist-info/RECORD
