Metadata-Version: 2.1
Name: pyrin
Version: 0.6.3
Summary: A rich, fast, performant and easy to use application framework to build apps using Flask on top of it.
Home-page: https://github.com/mononobi/pyrin
Author: mono
Author-email: mononobi@gmail.com
Maintainer: mono
Maintainer-email: mononobi@gmail.com
License: BSD-3-Clause
Project-URL: Code, https://github.com/mononobi/pyrin
Project-URL: Issue tracker, https://github.com/mononobi/pyrin/issues
Keywords: flask python sqlalchemy pyrin core alembic multi-database swagger-uiapplication-framework rest-api dependency-injection ioc admin-panel
Classifier: Development Status :: 5 - Production/Stable
Classifier: Environment :: Web Environment
Classifier: Framework :: Flask
Classifier: Intended Audience :: Developers
Classifier: License :: OSI Approved :: BSD License
Classifier: Operating System :: OS Independent
Classifier: Programming Language :: Python
Classifier: Programming Language :: Python :: 3.6
Classifier: Programming Language :: Python :: 3.7
Classifier: Programming Language :: Python :: 3.8
Classifier: Programming Language :: Python :: 3.9
Classifier: Programming Language :: Python :: 3.10
Classifier: Programming Language :: Python :: Implementation :: CPython
Classifier: Topic :: Internet :: WWW/HTTP :: Dynamic Content
Classifier: Topic :: Internet :: WWW/HTTP :: WSGI :: Application
Classifier: Topic :: Software Development :: Libraries :: Application Frameworks
Classifier: Topic :: Software Development :: Libraries :: Python Modules
Requires-Python: >=3.6
License-File: LICENSE
Requires-Dist: aniso8601 (==9.0.1)
Requires-Dist: bcrypt (==3.2.0)
Requires-Dist: pytz (==2023.3)
Requires-Dist: Flask (==2.0.2)
Requires-Dist: PyJWT (==2.2.0)
Requires-Dist: SQLAlchemy (==1.4.20)
Requires-Dist: colorama (==0.4.4)
Requires-Dist: python-dotenv (==0.18.0)
Requires-Dist: cryptography (==3.4.7)
Requires-Dist: flask-babel (==2.0.0)
Requires-Dist: babel (==2.9.1)
Requires-Dist: alembic (==1.6.5)
Requires-Dist: fire (==0.4.0)
Requires-Dist: sqlparse (==0.4.2)
Requires-Dist: titlecase (==2.3)
Requires-Dist: flasgger (==0.9.5)
Provides-Extra: celery
Requires-Dist: celery (==5.1.2) ; extra == 'celery'
Provides-Extra: docs
Requires-Dist: sphinx ; extra == 'docs'
Requires-Dist: sphinxcontrib-log-cabinet ; extra == 'docs'
Requires-Dist: sphinx-issues ; extra == 'docs'
Provides-Extra: memcached
Requires-Dist: pymemcache (==3.4.4) ; extra == 'memcached'
Provides-Extra: redis
Requires-Dist: redis (==3.5.3) ; extra == 'redis'
Provides-Extra: sentry
Requires-Dist: sentry-sdk (==1.1.0) ; extra == 'sentry'
Requires-Dist: blinker (==1.4) ; extra == 'sentry'
Provides-Extra: tests
Requires-Dist: aniso8601 (==9.0.1) ; extra == 'tests'
Requires-Dist: bcrypt (==3.2.0) ; extra == 'tests'
Requires-Dist: pytz (==2023.3) ; extra == 'tests'
Requires-Dist: Flask (==2.0.2) ; extra == 'tests'
Requires-Dist: PyJWT (==2.2.0) ; extra == 'tests'
Requires-Dist: SQLAlchemy (==1.4.20) ; extra == 'tests'
Requires-Dist: colorama (==0.4.4) ; extra == 'tests'
Requires-Dist: python-dotenv (==0.18.0) ; extra == 'tests'
Requires-Dist: cryptography (==3.4.7) ; extra == 'tests'
Requires-Dist: flask-babel (==2.0.0) ; extra == 'tests'
Requires-Dist: babel (==2.9.1) ; extra == 'tests'
Requires-Dist: alembic (==1.6.5) ; extra == 'tests'
Requires-Dist: fire (==0.4.0) ; extra == 'tests'
Requires-Dist: sqlparse (==0.4.2) ; extra == 'tests'
Requires-Dist: titlecase (==2.3) ; extra == 'tests'
Requires-Dist: flasgger (==0.9.5) ; extra == 'tests'
Requires-Dist: pytest (==6.2.4) ; extra == 'tests'
Requires-Dist: pytest-cov (==2.12.1) ; extra == 'tests'
Requires-Dist: pygments (==2.9.0) ; extra == 'tests'
